minivan/__init__.py
minivan/index.py
minivan/metrics.py
minivan_tools-0.1.5.dist-info/METADATA
minivan_tools-0.1.5.dist-info/WHEEL
minivan_tools-0.1.5.dist-info/RECORD
