Metadata-Version: 2.1
Name: minivan-tools
Version: 0.1.5
Summary: Exact nearest neighbor search library for those times when "approximate" just won't cut it (or is simply overkill)
Home-page: https://github.com/aismlv/minivan
License: Apache-2.0
Keywords: nearest neighbor search
Author: aismlv
Author-email: adilzhan.ismailov@gmail.com
Requires-Python: >=3.9,<3.12
Classifier: License :: OSI Approved :: Apache Software License
Classifier: Programming Language :: Python :: 3
Classifier: Programming Language :: Python :: 3.9
Classifier: Programming Language :: Python :: 3.10
Classifier: Programming Language :: Python :: 3.11
Requires-Dist: numpy (>=1.24.3,<2.0.0)
Project-URL: Repository, https://github.com/aismlv/minivan
